wte/__init__.py
wte/main.py
wte/src/__init__.py
wte/src/ebook.py
wte/src/util.py
wte/src/wattpad.py
wte-0.1.1.dist-info/LICENSE
wte-0.1.1.dist-info/METADATA
wte-0.1.1.dist-info/WHEEL
wte-0.1.1.dist-info/entry_points.txt
wte-0.1.1.dist-info/top_level.txt
wte-0.1.1.dist-info/RECORD
