Metadata-Version: 2.1
Name: wte
Version: 0.1.1
Summary: Convert content from the web to ebooks
Home-page: https://github.com/webalorn/web-to-ebook
Author: webalorn
Author-email: webalorn@gmail.com
License: UNKNOWN
Project-URL: Documentation, https://github.com/webalorn/web-to-ebook/blob/main/README.md
Project-URL: Source, https://github.com/webalorn/web-to-ebook
Platform: UNKNOWN
Classifier: Programming Language :: Python :: 3
Classifier: License :: OSI Approved :: MIT License
Classifier: Operating System :: OS Independent
Requires-Python: >=3
Requires-Dist: requests (>=2.24)
Requires-Dist: lxml (>=4.5)
Requires-Dist: pyquery (>=1.4)
Requires-Dist: ebooklib (>=0.17)
